whitebox_plugin_ui_components/__init__.py
whitebox_plugin_ui_components/jsx/buttons/Button.jsx
whitebox_plugin_ui_components/jsx/buttons/Button.test.jsx
whitebox_plugin_ui_components/jsx/buttons/PrimaryButton.jsx
whitebox_plugin_ui_components/jsx/buttons/PrimaryButton.test.jsx
whitebox_plugin_ui_components/jsx/buttons/SecondaryButton.jsx
whitebox_plugin_ui_components/jsx/buttons/SecondaryButton.test.jsx
whitebox_plugin_ui_components/jsx/buttons/TertiaryButton.jsx
whitebox_plugin_ui_components/jsx/buttons/TertiaryButton.test.jsx
whitebox_plugin_ui_components/jsx/common/InputContentArea.jsx
whitebox_plugin_ui_components/jsx/common/InputContentArea.test.jsx
whitebox_plugin_ui_components/jsx/common/Spinner.jsx
whitebox_plugin_ui_components/jsx/common/Spinner.test.jsx
whitebox_plugin_ui_components/jsx/scaffolding/FullScreenPopOut.jsx
whitebox_plugin_ui_components/jsx/scaffolding/ScrollableOverlay.jsx
whitebox_plugin_ui_components/whitebox_plugin_ui_components.py
whitebox_test_plugin_ui_components/__init__.py
whitebox_test_plugin_ui_components/test_whitebox_plugin_ui_components.py
whitebox_plugin_ui_components-0.1.3.dist-info/LICENSE
whitebox_plugin_ui_components-0.1.3.dist-info/METADATA
whitebox_plugin_ui_components-0.1.3.dist-info/WHEEL
whitebox_plugin_ui_components-0.1.3.dist-info/RECORD
